tatry/__init__.py
tatry/_version.py
tatry/config.py
tatry/exceptions.py
tatry/integrations/__init__.py
tatry/integrations/langchain.py
tatry/models/auth.py
tatry/models/retrieve.py
tatry/models/sources.py
tatry/models/utils.py
tatry/retrievers/__init__.py
tatry/retrievers/base.py
tatry/retrievers/tatry/__init__.py
tatry/retrievers/tatry/client.py
tatry/retrievers/tatry/endpoints.py
tatry-1.1.2.dist-info/METADATA
tatry-1.1.2.dist-info/WHEEL
tatry-1.1.2.dist-info/top_level.txt
tatry-1.1.2.dist-info/RECORD
