Metadata-Version: 2.2
Name: tatry
Version: 1.1.2
Summary: Python client for the Tatry Content Retrieval API
Author-email: TatryAI <opensource@tatry.dev>
License: MIT
Project-URL: Homepage, https://github.com/tatryai/tatry
Project-URL: Bug Tracker, https://github.com/tatryai/tatry/issues
Classifier: Programming Language :: Python :: 3
Classifier: Programming Language :: Python :: 3.8
Classifier: Programming Language :: Python :: 3.9
Classifier: Programming Language :: Python :: 3.10
Classifier: Programming Language :: Python :: 3.11
Classifier: License :: OSI Approved :: MIT License
Classifier: Operating System :: OS Independent
Classifier: Development Status :: 4 - Beta
Classifier: Intended Audience :: Developers
Classifier: Topic :: Software Development :: Libraries :: Python Modules
Requires-Python: >=3.8
Requires-Dist: requests>=2.25.0
Requires-Dist: pydantic>=2.0.0
Requires-Dist: tenacity>=8.0.0
Requires-Dist: urllib3>=2.0.0
Provides-Extra: langchain
Requires-Dist: langchain>=0.3.19; extra == "langchain"
Provides-Extra: test
Requires-Dist: pytest>=7.0.0; extra == "test"
Requires-Dist: pytest-cov>=4.0.0; extra == "test"
Requires-Dist: responses>=0.23.0; extra == "test"
Requires-Dist: pytest-mock>=3.10.0; extra == "test"
Requires-Dist: pytest-asyncio>=0.21.0; extra == "test"
Provides-Extra: dev
Requires-Dist: pytest>=7.0.0; extra == "dev"
Requires-Dist: pytest-cov>=4.0.0; extra == "dev"
Requires-Dist: responses>=0.23.0; extra == "dev"
Requires-Dist: pytest-mock>=3.10.0; extra == "dev"
Requires-Dist: pytest-asyncio>=0.21.0; extra == "dev"
Requires-Dist: black>=22.0.0; extra == "dev"
Requires-Dist: isort>=5.0.0; extra == "dev"
Requires-Dist: mypy>=1.0.0; extra == "dev"
Requires-Dist: flake8>=4.0.0; extra == "dev"
Requires-Dist: types-requests>=2.31.0; extra == "dev"
